vending_machine.v
module vending_machine(
    input clk,
    input rst,
    input [1:0] in, // 00 -> 0 rs, 01 -> 5 rs, 10 -> 10 rs
    output reg out,
    output reg [1:0] change
);

// Define the states using parameters
parameter s0 = 2'b00; // State for 0 rs
parameter s1 = 2'b01; // State for 5 rs
parameter s2 = 2'b10; // State for 10 rs

// Registers for current and next state
reg [1:0] c_state, n_state;

// Always block to update the current state on the positive edge of the clock
always @(posedge clk) begin
    if (rst == 1) begin
        // Reset condition
        c_state <= s0;
        n_state <= s0;
        change <= 2'b00;
        out <= 0;
    end else begin
        // Update current state to next state
        c_state <= n_state;
    end
end

// Combinational logic block to determine next state and outputs
always @(*) begin
    case (c_state)
        s0: begin // State 0: 0 rs
            if (in == 2'b00) begin
                n_state = s0;
                out = 0;
                change = 2'b00;
            end else if (in == 2'b01) begin
                n_state = s1;
                out = 0;
                change = 2'b00;
            end else if (in == 2'b10) begin
                n_state = s2;
                out = 0;
                change = 2'b00;
            end
        end

        s1: begin // State 1: 5 rs
            if (in == 2'b00) begin
                n_state = s0;
                out = 0;
                change = 2'b01; // Change returned: 5 rs
            end else if (in == 2'b01) begin
                n_state = s2;
                out = 0;
                change = 2'b00;
            end else if (in == 2'b10) begin
                n_state = s0;
                out = 1; // Dispense the item
                change = 2'b00;
            end
        end

        s2: begin // State 2: 10 rs
            if (in == 2'b00) begin
                n_state = s0;
                out = 0;
                change = 2'b10; // Change returned: 10 rs
            end else if (in == 2'b01) begin
                n_state = s0;
                out = 1; // Dispense the item
                change = 2'b01; // Change returned: 5 rs
            end else if (in == 2'b10) begin
                n_state = s0;
                out = 1; // Dispense the item
                change = 2'b10; // Change returned: 10 rs
            end
        end

        default: begin
            n_state = s0;
            out = 0;
            change = 2'b00;
        end
    endcase
end

endmodule

tb.v
module vending_machine_tb;

// Inputs
reg clk;
reg [1:0] in;
reg rst;

// Outputs
wire out;
wire [1:0] change;

// Instantiate the Unit Under Test (UUT)
vending_machine uut (
    .clk(clk), 
    .in(in), 
    .out(out),
    .rst(rst),
    .change(change)
);

initial begin
    // Initialize Inputs
    $dumpfile("vending_machine.vcd");
    $dumpvars(0, vending_machine_tb);

    rst = 1;
    clk = 0;
    in = 2'b00; // Initial value of input

    #6 rst = 0; // De-assert reset after 6 time units

    // Apply test cases
    #11 in = 2'b01; // Insert 5 rs
    #16 in = 2'b01; // Insert another 5 rs
    #25 $finish;    // End the simulation
end

// Clock generation
always #5 clk = ~clk;

// Monitor changes in output and change
initial begin
    $monitor($time, " in: %b, out: %b, change: %b", in, out, change);
end

endmodule

vending_machine.vcd
$date
	Fri Aug 30 02:58:48 2024
$end
$version
	Icarus Verilog
$end
$timescale
	1s
$end
$scope module vending_machine_tb $end
$var wire 1 ! out $end
$var wire 2 " change [1:0] $end
$var reg 1 # clk $end
$var reg 2 $ in [1:0] $end
$var reg 1 % rst $end
$scope module uut $end
$var wire 1 # clk $end
$var wire 2 & in [1:0] $end
$var wire 1 % rst $end
$var parameter 2 ' s0 $end
$var parameter 2 ( s1 $end
$var parameter 2 ) s2 $end
$var reg 2 * c_state [1:0] $end
$var reg 2 + change [1:0] $end
$var reg 2 , n_state [1:0] $end
$var reg 1 ! out $end
$upscope $end
$upscope $end
$enddefinitions $end
$comment Show the parameter values. $end
$dumpall
b10 )
b1 (
b0 '
$end
#0
$dumpvars
b0 ,
b0 +
bx *
b0 &
1%
b0 $
0#
b0 "
0!
$end
#5
b0 *
1#
#6
0%
#10
0#
#15
1#
#17
b1 ,
b1 $
b1 &
#20
0#
#25
b10 ,
b1 *
1#
#30
0#
#35
b1 "
b1 +
1!
b0 ,
b10 *
1#
#40
0#
#45
b0 "
b0 +
0!
b1 ,
b0 *
1#
#50
0#
#55
b10 ,
b1 *
1#
